sikriml/__init__.py
sikriml/config.py
sikriml/environment/__init__.py
sikriml/environment/aml_environment.py
sikriml/environment/configs/__init__.py
sikriml/environment/configs/environment_config.py
sikriml/environment/errors/__init__.py
sikriml/environment/errors/aml_build_image_error.py
sikriml/experiment/__init__.py
sikriml/experiment/experiment_abs.py
sikriml/experiment/pipeline/__init__.py
sikriml/experiment/pipeline/pipeline_experiment.py
sikriml/experiment/script/__init__.py
sikriml/experiment/script/script_experiment.py
sikriml/helpers/__init__.py
sikriml/helpers/io/__init__.py
sikriml/helpers/io/json_file_helper.py
sikriml/helpers/io/txt_file_helper.py
sikriml/helpers/io/yaml_file_helper.py
sikriml/helpers/io/abstracts/__init__.py
sikriml/helpers/io/abstracts/serializable_interface.py
sikriml/models/__init__.py
sikriml/models/ner/__init__.py
sikriml/models/ner/processor_base.py
sikriml/models/ner/score_entity.py
sikriml/models/ner/score_label.py
sikriml/models/ner/flair/__init__.py
sikriml/models/ner/flair/flair_processor.py
sikriml/models/ner/rule/__init__.py
sikriml/models/ner/rule/rule_processor.py
sikriml/models/ner/rule/handlers/__init__.py
sikriml/models/ner/rule/handlers/account_number_handler.py
sikriml/models/ner/rule/handlers/card_number_handler.py
sikriml/models/ner/rule/handlers/number_handler.py
sikriml/models/ner/rule/handlers/personal_number_handler.py
sikriml/models/ner/rule/handlers/url_handler.py
sikriml/models/ner/rule/handlers/word_list_handler.py
sikriml/models/ner/rule/handlers/year_handler.py
sikriml/models/ner/rule/handlers/abstracts/__init__.py
sikriml/models/ner/rule/handlers/abstracts/entity_handler.py
sikriml/models/ner/rule/handlers/abstracts/regex_handler.py
sikriml/models/ner/rule/handlers/abstracts/regex_handler_decorator.py
sikriml/models/ner/rule/models/__init__.py
sikriml/models/ner/rule/models/card_type.py
sikriml/models/ner/rule/services/__init__.py
sikriml/models/ner/rule/services/file_loader.py
sikriml-0.1.25.dist-info/METADATA
sikriml-0.1.25.dist-info/WHEEL
sikriml-0.1.25.dist-info/top_level.txt
sikriml-0.1.25.dist-info/RECORD
