Metadata-Version: 2.1
Name: sikriml
Version: 0.1.25
Summary: A small example package
Home-page: https://github.com/pypa/sampleproject
Author: Example Author
Author-email: author@example.com
Project-URL: Bug Tracker, https://github.com/pypa/sampleproject/issues
Classifier: Programming Language :: Python :: 3
Classifier: License :: OSI Approved :: MIT License
Classifier: Operating System :: OS Independent
Requires-Python: >=3.8
Requires-Dist: nltk (>=3.6.3)
Requires-Dist: spacy (>=3.2)
Requires-Dist: flair (>=0.11)
Requires-Dist: azureml-sdk (>=1.41.0)
Requires-Dist: pydash (>=5.1.0)
Requires-Dist: intervaltree (>=3.1.0)
Requires-Dist: dacite (>=1.6.0)
